djangocms_fullslider/__init__.py
djangocms_fullslider/cms_plugins.py
djangocms_fullslider/forms.py
djangocms_fullslider/models.py
djangocms_fullslider/settings.py
djangocms_fullslider/tests.py
djangocms_fullslider-1.0.0.dist-info/DESCRIPTION.rst
djangocms_fullslider-1.0.0.dist-info/METADATA
djangocms_fullslider-1.0.0.dist-info/RECORD
djangocms_fullslider-1.0.0.dist-info/WHEEL
djangocms_fullslider-1.0.0.dist-info/metadata.json
djangocms_fullslider-1.0.0.dist-info/top_level.txt
