Metadata-Version: 2.0
Name: djangocms-fullslider
Version: 1.0.0
Summary: Full page slider plugin for django CMS
Home-page: https://github.com/Logicify/djangocms-fullslider
Author: Dmitriy Selischev
Author-email: dmitriy.selischev@logicify.com
License: MIT
Keywords: django cms plugin fullpage slider background image
Platform: UNKNOWN
Classifier: Development Status :: 3 - Alpha
Classifier: Intended Audience :: Developers
Classifier: Topic :: Software Development :: Build Tools
Classifier: License :: OSI Approved :: MIT License
Classifier: Programming Language :: Python :: 3
Classifier: Programming Language :: Python :: 3.5
Classifier: Programming Language :: Python :: 3.6
Requires-Dist: django
Requires-Dist: django-cms
Requires-Dist: django-sekizai
Requires-Dist: cmsplugin-filer
Provides-Extra: dev
Provides-Extra: test
